feature_transform/__init__.py
feature_transform/helper.py
feature_transform/example/notebook/demo.py
feature_transform/example/spec/basic.yaml
feature_transform/example/spec/name-intcol.yaml
feature_transform/example/spec/pipeline.yaml
feature_transform/example/spec/settings.yaml
feature_transform/example/spec/wine/x.yaml
feature_transform/example/spec/wine/y.yaml
feature_transform/validator/spec.py
feature_transform-1.0.1.dist-info/METADATA
feature_transform-1.0.1.dist-info/WHEEL
feature_transform-1.0.1.dist-info/licenses/LICENSE
feature_transform-1.0.1.dist-info/RECORD
