Metadata-Version: 2.4
Name: feature-transform
Version: 1.0.1
Summary: Build Scikit ColumnTransformers by specifying configs.
License-File: LICENSE
Requires-Python: >=3.10
Requires-Dist: pandas>=2.0.0
Requires-Dist: polars>=1.0.0
Requires-Dist: pydantic>=2.10.4
Requires-Dist: pyyaml>=6.0.2
Requires-Dist: scikit-learn>=1.2.0
